thonnycontrib/openai_gpt/__init__.py
thonnycontrib/openai_gpt/gpt_tool.py
thonny_openai_gpt-0.1.26.dist-info/METADATA
thonny_openai_gpt-0.1.26.dist-info/WHEEL
thonny_openai_gpt-0.1.26.dist-info/entry_points.txt
thonny_openai_gpt-0.1.26.dist-info/top_level.txt
thonny_openai_gpt-0.1.26.dist-info/RECORD
