Metadata-Version: 2.4
Name: thonny-openai-gpt
Version: 0.1.26
Summary: OpenAI GPT for Thonny IDE
Home-page: https://github.com/Oliver0804/thonny_openai_gpt
Author: Oliver0804
Author-email: Oliver0804 <icetzsr@gmail.com>
License: MIT
Platform: Windows
Platform: macOS
Platform: Linux
Classifier: Programming Language :: Python :: 3
Classifier: License :: OSI Approved :: MIT License
Classifier: Operating System :: OS Independent
Classifier: Environment :: Plugins
Classifier: Intended Audience :: Education
Classifier: Intended Audience :: Developers
Requires-Python: >=3.7
Requires-Dist: openai>=1.75.0
Dynamic: author
Dynamic: home-page
Dynamic: platform
Dynamic: requires-python
